{
  "_fv": 47,
  "_type": "recipe",
  "definition": {
    "recipeType": "Crafting",
    "recipeRetstackSize": 1,
    "group": "",
    "cookingBookCategory": "MISC",
    "xpReward": 0.0,
    "cookingTime": 200,
    "craftingBookCategory": "MISC",
    "recipeShapeless": true,
    "recipeSlots": [
      {
        "value": ""
      },
      {
        "value": ""
      },
      {
        "value": ""
      },
      {
        "value": "Items.DYE#12"
      },
      {
        "value": "CUSTOM:BlankTape"
      },
      {
        "value": "Blocks.SOUL_TORCH"
      },
      {
        "value": ""
      },
      {
        "value": "Items.WATER_BUCKET"
      },
      {
        "value": ""
      }
    ],
    "recipeReturnStack": {
      "value": "CUSTOM:CassetteMonster"
    },
    "name": "recipe_monster",
    "namespace": "mod"
  }
}